furthrmind/__init__.py
furthrmind/collection/__init__.py
furthrmind/collection/baseclass.py
furthrmind/collection/category.py
furthrmind/collection/column.py
furthrmind/collection/comboboxentry.py
furthrmind/collection/datatable.py
furthrmind/collection/experiment.py
furthrmind/collection/field.py
furthrmind/collection/fielddata.py
furthrmind/collection/file.py
furthrmind/collection/group.py
furthrmind/collection/import_collection.py
furthrmind/collection/project.py
furthrmind/collection/researchitem.py
furthrmind/collection/sample.py
furthrmind/collection/unit.py
furthrmind/file_loader.py
furthrmind/utils.py
furthrmind-0.2.10.dist-info/LICENSE
furthrmind-0.2.10.dist-info/METADATA
furthrmind-0.2.10.dist-info/WHEEL
furthrmind-0.2.10.dist-info/RECORD
